phenex/__init__.py
phenex/ibis_connect.py
phenex/mappers.py
phenex/node.py
phenex/node_manager.py
phenex/sim.py
phenex/tables.py
phenex/aggregators/__init__.py
phenex/aggregators/aggregator.py
phenex/codelists/__init__.py
phenex/codelists/codelists.py
phenex/derived_tables/__init__.py
phenex/derived_tables/combine_overlapping_periods.py
phenex/derived_tables/events_to_time_range.py
phenex/filters/__init__.py
phenex/filters/categorical_filter.py
phenex/filters/codelist_filter.py
phenex/filters/date_filter.py
phenex/filters/filter.py
phenex/filters/relative_time_range_filter.py
phenex/filters/time_range_filter.py
phenex/filters/value.py
phenex/filters/value_filter.py
phenex/phenotypes/__init__.py
phenex/phenotypes/age_phenotype.py
phenex/phenotypes/bin_phenotype.py
phenex/phenotypes/categorical_phenotype.py
phenex/phenotypes/codelist_phenotype.py
phenex/phenotypes/cohort.py
phenex/phenotypes/computation_graph_phenotypes.py
phenex/phenotypes/death_phenotype.py
phenex/phenotypes/event_count_phenotype.py
phenex/phenotypes/functions.py
phenex/phenotypes/measurement_change_phenotype.py
phenex/phenotypes/measurement_phenotype.py
phenex/phenotypes/phenotype.py
phenex/phenotypes/sex_phenotype.py
phenex/phenotypes/time_range_count_phenotype.py
phenex/phenotypes/time_range_day_count_phenotype.py
phenex/phenotypes/time_range_days_to_next_range_phenotype.py
phenex/phenotypes/time_range_phenotype.py
phenex/phenotypes/time_shift_phenotype.py
phenex/phenotypes/user_defined_phenotype.py
phenex/phenotypes/within_same_encounter_phenotype.py
phenex/phenotypes/factory/__init__.py
phenex/phenotypes/factory/chadsvasc.py
phenex/phenotypes/factory/isth_major_bleed.py
phenex/phenotypes/factory/one_inpatient_two_outpatient.py
phenex/phenotypes/factory/stackable_regimen.py
phenex/reporting/__init__.py
phenex/reporting/cohort_explorer.py
phenex/reporting/counts.py
phenex/reporting/report_drafter.py
phenex/reporting/reporter.py
phenex/reporting/table1.py
phenex/reporting/table2.py
phenex-0.7.8.dist-info/licenses/LICENSE
phenex-0.7.8.dist-info/METADATA
phenex-0.7.8.dist-info/WHEEL
phenex-0.7.8.dist-info/top_level.txt
phenex-0.7.8.dist-info/RECORD
