Metadata-Version: 2.4
Name: phenex
Version: 0.7.8
Summary: PhenEx is a Python package for analysis-ready datasets from real-world data
Home-page: https://github.com/Bayer-Group/PhenEx
Author: Bayer AG
Author-email: alexander.hartenstein@bayer.com
Classifier: Programming Language :: Python :: 3
Classifier: License :: OSI Approved :: BSD License
Classifier: Operating System :: OS Independent
Requires-Python: >=3.12
License-File: LICENSE
Requires-Dist: psycopg2-binary==2.9.11
Requires-Dist: ibis-framework[duckdb,examples,snowflake]==9.5.0
Requires-Dist: black==24.10.0
Requires-Dist: python-dotenv
Requires-Dist: pytest
Requires-Dist: snowflake-connector-python
Requires-Dist: mkdocs
Requires-Dist: mkdocs-material
Requires-Dist: mkdocstrings[python]
Requires-Dist: mkdocs-jupyter
Requires-Dist: setuptools
Requires-Dist: openpyxl
Requires-Dist: deepdiff
Requires-Dist: lifelines==0.30.0
Requires-Dist: matplotlib==3.10.1
Requires-Dist: reportlab==4.0.7
Requires-Dist: python-docx==1.1.0
Requires-Dist: tabulate
Requires-Dist: openai==2.14.0
Requires-Dist: bokeh
Dynamic: author
Dynamic: author-email
Dynamic: classifier
Dynamic: description
Dynamic: description-content-type
Dynamic: home-page
Dynamic: license-file
Dynamic: requires-dist
Dynamic: requires-python
Dynamic: summary
